pyneuroutils/datasets/__init__.py
pyneuroutils/datasets/diabetes.py
pyneuroutils/datasets/iris.py
pyneuroutils/mefd/__init__.py
pyneuroutils/mefd/client.py
pyneuroutils/statistics/__init__.py
pyneuroutils/statistics/statistics.py
pyneuroutils/transforms/__init__.py
pyneuroutils/transforms/compose.py
pyneuroutils/transforms/crop.py
pyneuroutils/transforms/diff.py
pyneuroutils/transforms/filtfilt.py
pyneuroutils/transforms/sample.py
pyneuroutils/transforms/segment.py
pyneuroutils/transforms/spectrogram.py
pyneuroutils/transforms/transform.py
pyneuroutils/transforms/zscore.py
pyneuroutils/utilities/__init__.py
pyneuroutils/utilities/utilities.py
pyneuroutils-1.0.16.dist-info/LICENSE
pyneuroutils-1.0.16.dist-info/METADATA
pyneuroutils-1.0.16.dist-info/WHEEL
pyneuroutils-1.0.16.dist-info/top_level.txt
pyneuroutils-1.0.16.dist-info/RECORD
