Metadata-Version: 2.1
Name: pyneuroutils
Version: 1.0.16
Summary: UNKNOWN
Home-page: https://github.com/xnejed07/pyneuroutils
Author: Petr Nejedly
Author-email: xnejed07@gmail.com
License: MIT
Platform: UNKNOWN
Requires-Dist: numpy
Requires-Dist: scikit-learn
Requires-Dist: matplotlib
Requires-Dist: pandas
